pyoci/__init__.py
pyoci/base_types.py
pyoci/common.py
pyoci/image/__init__.py
pyoci/image/config.py
pyoci/image/descriptor.py
pyoci/image/digest.py
pyoci/image/layout.py
pyoci/image/manifest.py
pyoci/image/platform.py
pyoci/image/well_known.py
pyoci/runtime/__init__.py
pyoci/runtime/client/__init__.py
pyoci/runtime/client/any.py
pyoci/runtime/client/errors.py
pyoci/runtime/client/runc.py
pyoci/runtime/client/runsc.py
pyoci/runtime/client/utils.py
pyoci/runtime/client/spec/features.py
pyoci/runtime/client/spec/linux_features.py
pyoci/runtime/client/spec/state.py
pyoci/runtime/client/specific/crun.py
pyoci/runtime/client/specific/runc/__init__.py
pyoci/runtime/client/specific/runc/constraints.py
pyoci/runtime/client/specific/runc/events.py
pyoci/runtime/config/__init__.py
pyoci/runtime/config/filesystem.py
pyoci/runtime/config/hooks.py
pyoci/runtime/config/process.py
pyoci/runtime/config/platform/solaris.py
pyoci/runtime/config/platform/vm.py
pyoci/runtime/config/platform/windows.py
pyoci/runtime/config/platform/zos.py
pyoci/runtime/config/platform/linux/__init__.py
pyoci/runtime/config/platform/linux/devices.py
pyoci/runtime/config/platform/linux/seccomp.py
pyoci/runtime/config/templates/default.py
pyoci/utils/goplatform.py
pyoci/utils/idmap.py
pyoci/utils/sandboxed_untar.py
pyoci/utils/size.py
pyoci/utils/userns.py
pyoci-0.3.4.dist-info/METADATA
pyoci-0.3.4.dist-info/WHEEL
pyoci-0.3.4.dist-info/licenses/LICENSE
pyoci-0.3.4.dist-info/RECORD
