Metadata-Version: 2.4
Name: pyoci
Version: 0.3.4
Summary: OCI-runtime spec represented as python objects.
Project-URL: Homepage, https://github.com/hazyfossa/pyoci
Project-URL: Issues, https://github.com/hazyfossa/pyoci/issues
Author-email: hazyfossa <hazyfossa@gmail.com>
License-File: LICENSE
Classifier: Intended Audience :: Developers
Classifier: License :: OSI Approved :: MIT License
Classifier: Programming Language :: Python :: 3
Requires-Python: >=3.13
Requires-Dist: msgspec<1,>=0.19.0
